setup.py
charmworldlib/__init__.py
charmworldlib/api.py
charmworldlib/bundle.py
charmworldlib/charm.py
charmworldlib/utils.py
charmworldlib.egg-info/PKG-INFO
charmworldlib.egg-info/SOURCES.txt
charmworldlib.egg-info/dependency_links.txt
charmworldlib.egg-info/top_level.txt