Metadata-Version: 1.1
Name: charmworldlib
Version: 0.3.0
Summary: Library to access charmworld data
Home-page: https://launchpad.net/charmworldlib
Author: Marco Ceppi
Author-email: marco@ceppi.net
License: GPL v3
Platform: UNKNOWN
Classifier: Development Status :: 5 - Production/Stable
Classifier: Intended Audience :: Developers
Classifier: Programming Language :: Python
Classifier: License :: OSI Approved :: GNU General Public License v3 (GPLv3)
